kingfisher/__init__.py
kingfisher/ena.py
kingfisher/exception.py
kingfisher/location.py
kingfisher/md5sum.py
kingfisher/sra_metadata.py
kingfisher/version.py
kingfisher/data/asperaweb_id_dsa.openssh
kingfisher-0.4.1.data/data/LICENCE.txt
kingfisher-0.4.1.data/data/README.md
kingfisher-0.4.1.data/scripts/kingfisher
kingfisher-0.4.1.dist-info/LICENCE.txt
kingfisher-0.4.1.dist-info/METADATA
kingfisher-0.4.1.dist-info/WHEEL
kingfisher-0.4.1.dist-info/top_level.txt
kingfisher-0.4.1.dist-info/RECORD
