Metadata-Version: 2.1
Name: kingfisher
Version: 0.4.1
Summary: Download/extract biological FASTA/Q read data and metadata
Home-page: https://github.com/wwood/kingfisher-download
Author: Ben Woodcroft
Author-email: benjwoodcroft@gmail.com
License: GPL3+
Classifier: Topic :: Scientific/Engineering :: Bio-Informatics
License-File: LICENCE.txt
Requires-Dist: extern
Requires-Dist: requests
Requires-Dist: tqdm
Requires-Dist: pandas
Requires-Dist: bird-tool-utils
Requires-Dist: pyarrow
